{
  "updated": "2026-06-28T10:00:26",
  "weight": 86.1,
  "weight_date": "2026-06-28",
  "training_days_total": 110,
  "last_training_day": "2026-06-28",
  "lifts": {
    "Squat": {
      "last_date": "2026-06-28",
      "last_weight": 95.0,
      "last_volume": 2122.5,
      "pr": false,
      "pr_weight": 100.0
    },
    "Deadlift": {
      "last_date": "2026-06-27",
      "last_weight": 107.5,
      "last_volume": 1685.0,
      "pr": true,
      "pr_weight": 107.5
    },
    "Bench": {
      "last_date": "2026-06-27",
      "last_weight": 82.5,
      "last_volume": 1600.0,
      "pr": false,
      "pr_weight": 85.0
    },
    "DB Bench x2": {
      "last_date": "2026-06-23",
      "last_weight": 72.0,
      "last_volume": 1648.0,
      "pr": true,
      "pr_weight": 72.0
    },
    "OHP": {
      "last_date": "2026-06-28",
      "last_weight": 40.0,
      "last_volume": 1310.0,
      "pr": false,
      "pr_weight": 52.5
    },
    "Lat PD": {
      "last_date": "2026-06-09",
      "last_weight": 55.0,
      "last_volume": 1450.0,
      "pr": false,
      "pr_weight": 60.0
    },
    "DIP-BW": {
      "last_date": "2026-05-28",
      "last_weight": 59.1,
      "last_volume": 2364.0,
      "pr": false,
      "pr_weight": 87.8
    },
    "Front Squat": {
      "last_date": "2026-04-13",
      "last_weight": 40.0,
      "last_volume": 1040.0,
      "pr": false,
      "pr_weight": 60.0
    },
    "Row": {
      "last_date": "2026-06-23",
      "last_weight": 60.0,
      "last_volume": 2250.0,
      "pr": true,
      "pr_weight": 60.0
    },
    "Hip Thrust": {
      "last_date": "2026-06-16",
      "last_weight": 25.0,
      "last_volume": 600.0,
      "pr": false,
      "pr_weight": 30.0
    },
    "Face Pull": {
      "last_date": "2026-06-10",
      "last_weight": 20.0,
      "last_volume": 585.0,
      "pr": true,
      "pr_weight": 20.0
    },
    "Cable Row": {
      "last_date": "2026-06-17",
      "last_weight": 40.0,
      "last_volume": 1760.0,
      "pr": false,
      "pr_weight": 60.0
    },
    "Abductor": {
      "last_date": "2026-06-17",
      "last_weight": 30.0,
      "last_volume": 1320.0,
      "pr": true,
      "pr_weight": 30.0
    },
    "Leg Curl": {
      "last_date": "2026-05-27",
      "last_weight": 25.0,
      "last_volume": 875.0,
      "pr": false,
      "pr_weight": 35.0
    },
    "Block Pull": {
      "last_date": "2026-06-08",
      "last_weight": 102.5,
      "last_volume": 1890.0,
      "pr": true,
      "pr_weight": 102.5
    }
  }
}